{"data":[{"hovertemplate":"\u003cb\u003e%{hovertext}\u003c\u002fb\u003e\u003cbr\u003e\u003cbr\u003eState=Alabama\u003cbr\u003eYear=%{x}\u003cbr\u003eTotal Ocean GDP=%{marker.size}\u003cextra\u003e\u003c\u002fextra\u003e","hovertext":[42.068312301726806,44.57310192057757,45.47873299859467],"legendgroup":"","marker":{"color":"#636efa","size":[42.068312301726806,44.57310192057757,45.47873299859467],"sizemode":"area","sizeref":0.11436863721259133,"symbol":"circle"},"mode":"markers","name":"","orientation":"v","showlegend":false,"x":[2005,2015,2021],"xaxis":"x","y":[42.068312301726806,44.57310192057757,45.47873299859467],"yaxis":"y","type":"scatter"}],"layout":{"template":{"data":{"histogram2dcontour":[{"type":"histogram2dcontour","colorbar":{"outlinewidth":0,"ticks":""},"colorscale":[[0.0,"#0d0887"],[0.1111111111111111,"#46039f"],[0.2222222222222222,"#7201a8"],[0.3333333333333333,"#9c179e"],[0.4444444444444444,"#bd3786"],[0.5555555555555556,"#d8576b"],[0.6666666666666666,"#ed7953"],[0.7777777777777778,"#fb9f3a"],[0.8888888888888888,"#fdca26"],[1.0,"#f0f921"]]}],"choropleth":[{"type":"choropleth","colorbar":{"outlinewidth":0,"ticks":""}}],"histogram2d":[{"type":"histogram2d","colorbar":{"outlinewidth":0,"ticks":""},"colorscale":[[0.0,"#0d0887"],[0.1111111111111111,"#46039f"],[0.2222222222222222,"#7201a8"],[0.3333333333333333,"#9c179e"],[0.4444444444444444,"#bd3786"],[0.5555555555555556,"#d8576b"],[0.6666666666666666,"#ed7953"],[0.7777777777777778,"#fb9f3a"],[0.8888888888888888,"#fdca26"],[1.0,"#f0f921"]]}],"heatmap":[{"type":"heatmap","colorbar":{"outlinewidth":0,"ticks":""},"colorscale":[[0.0,"#0d0887"],[0.1111111111111111,"#46039f"],[0.2222222222222222,"#7201a8"],[0.3333333333333333,"#9c179e"],[0.4444444444444444,"#bd3786"],[0.5555555555555556,"#d8576b"],[0.6666666666666666,"#ed7953"],[0.7777777777777778,"#fb9f3a"],[0.8888888888888888,"#fdca26"],[1.0,"#f0f921"]]}],"heatmapgl":[{"type":"heatmapgl","colorbar":{"outlinewidth":0,"ticks":""},"colorscale":[[0.0,"#0d0887"],[0.1111111111111111,"#46039f"],[0.2222222222222222,"#7201a8"],[0.3333333333333333,"#9c179e"],[0.4444444444444444,"#bd3786"],[0.5555555555555556,"#d8576b"],[0.6666666666666666,"#ed7953"],[0.7777777777777778,"#fb9f3a"],[0.8888888888888888,"#fdca26"],[1.0,"#f0f921"]]}],"contourcarpet":[{"type":"contourcarpet","colorbar":{"outlinewidth":0,"ticks":""}}],"contour":[{"type":"contour","colorbar":{"outlinewidth":0,"ticks":""},"colorscale":[[0.0,"#0d0887"],[0.1111111111111111,"#46039f"],[0.2222222222222222,"#7201a8"],[0.3333333333333333,"#9c179e"],[0.4444444444444444,"#bd3786"],[0.5555555555555556,"#d8576b"],[0.6666666666666666,"#ed7953"],[0.7777777777777778,"#fb9f3a"],[0.8888888888888888,"#fdca26"],[1.0,"#f0f921"]]}],"surface":[{"type":"surface","colorbar":{"outlinewidth":0,"ticks":""},"colorscale":[[0.0,"#0d0887"],[0.1111111111111111,"#46039f"],[0.2222222222222222,"#7201a8"],[0.3333333333333333,"#9c179e"],[0.4444444444444444,"#bd3786"],[0.5555555555555556,"#d8576b"],[0.6666666666666666,"#ed7953"],[0.7777777777777778,"#fb9f3a"],[0.8888888888888888,"#fdca26"],[1.0,"#f0f921"]]}],"mesh3d":[{"type":"mesh3d","colorbar":{"outlinewidth":0,"ticks":""}}],"scatter":[{"fillpattern":{"fillmode":"overlay","size":10,"solidity":0.2},"type":"scatter"}],"parcoords":[{"type":"parcoords","line":{"colorbar":{"outlinewidth":0,"ticks":""}}}],"scatterpolargl":[{"type":"scatterpolargl","marker":{"colorbar":{"outlinewidth":0,"ticks":""}}}],"bar":[{"error_x":{"color":"#2a3f5f"},"error_y":{"color":"#2a3f5f"},"marker":{"line":{"color":"#E5ECF6","width":0.5},"pattern":{"fillmode":"overlay","size":10,"solidity":0.2}},"type":"bar"}],"scattergeo":[{"type":"scattergeo","marker":{"colorbar":{"outlinewidth":0,"ticks":""}}}],"scatterpolar":[{"type":"scatterpolar","marker":{"colorbar":{"outlinewidth":0,"ticks":""}}}],"histogram":[{"marker":{"pattern":{"fillmode":"overlay","size":10,"solidity":0.2}},"type":"histogram"}],"scattergl":[{"type":"scattergl","marker":{"colorbar":{"outlinewidth":0,"ticks":""}}}],"scatter3d":[{"type":"scatter3d","line":{"colorbar":{"outlinewidth":0,"ticks":""}},"marker":{"colorbar":{"outlinewidth":0,"ticks":""}}}],"scattermapbox":[{"type":"scattermapbox","marker":{"colorbar":{"outlinewidth":0,"ticks":""}}}],"scatterternary":[{"type":"scatterternary","marker":{"colorbar":{"outlinewidth":0,"ticks":""}}}],"scattercarpet":[{"type":"scattercarpet","marker":{"colorbar":{"outlinewidth":0,"ticks":""}}}],"carpet":[{"aaxis":{"endlinecolor":"#2a3f5f","gridcolor":"white","linecolor":"white","minorgridcolor":"white","startlinecolor":"#2a3f5f"},"baxis":{"endlinecolor":"#2a3f5f","gridcolor":"white","linecolor":"white","minorgridcolor":"white","startlinecolor":"#2a3f5f"},"type":"carpet"}],"table":[{"cells":{"fill":{"color":"#EBF0F8"},"line":{"color":"white"}},"header":{"fill":{"color":"#C8D4E3"},"line":{"color":"white"}},"type":"table"}],"barpolar":[{"marker":{"line":{"color":"#E5ECF6","width":0.5},"pattern":{"fillmode":"overlay","size":10,"solidity":0.2}},"type":"barpolar"}],"pie":[{"automargin":true,"type":"pie"}]},"layout":{"autotypenumbers":"strict","colorway":["#636efa","#EF553B","#00cc96","#ab63fa","#FFA15A","#19d3f3","#FF6692","#B6E880","#FF97FF","#FECB52"],"font":{"color":"#2a3f5f"},"hovermode":"closest","hoverlabel":{"align":"left"},"paper_bgcolor":"white","plot_bgcolor":"#E5ECF6","polar":{"bgcolor":"#E5ECF6","angularaxis":{"gridcolor":"white","linecolor":"white","ticks":""},"radialaxis":{"gridcolor":"white","linecolor":"white","ticks":""}},"ternary":{"bgcolor":"#E5ECF6","aaxis":{"gridcolor":"white","linecolor":"white","ticks":""},"baxis":{"gridcolor":"white","linecolor":"white","ticks":""},"caxis":{"gridcolor":"white","linecolor":"white","ticks":""}},"coloraxis":{"colorbar":{"outlinewidth":0,"ticks":""}},"colorscale":{"sequential":[[0.0,"#0d0887"],[0.1111111111111111,"#46039f"],[0.2222222222222222,"#7201a8"],[0.3333333333333333,"#9c179e"],[0.4444444444444444,"#bd3786"],[0.5555555555555556,"#d8576b"],[0.6666666666666666,"#ed7953"],[0.7777777777777778,"#fb9f3a"],[0.8888888888888888,"#fdca26"],[1.0,"#f0f921"]],"sequentialminus":[[0.0,"#0d0887"],[0.1111111111111111,"#46039f"],[0.2222222222222222,"#7201a8"],[0.3333333333333333,"#9c179e"],[0.4444444444444444,"#bd3786"],[0.5555555555555556,"#d8576b"],[0.6666666666666666,"#ed7953"],[0.7777777777777778,"#fb9f3a"],[0.8888888888888888,"#fdca26"],[1.0,"#f0f921"]],"diverging":[[0,"#8e0152"],[0.1,"#c51b7d"],[0.2,"#de77ae"],[0.3,"#f1b6da"],[0.4,"#fde0ef"],[0.5,"#f7f7f7"],[0.6,"#e6f5d0"],[0.7,"#b8e186"],[0.8,"#7fbc41"],[0.9,"#4d9221"],[1,"#276419"]]},"xaxis":{"gridcolor":"white","linecolor":"white","ticks":"","title":{"standoff":15},"zerolinecolor":"white","automargin":true,"zerolinewidth":2},"yaxis":{"gridcolor":"white","linecolor":"white","ticks":"","title":{"standoff":15},"zerolinecolor":"white","automargin":true,"zerolinewidth":2},"scene":{"xaxis":{"backgroundcolor":"#E5ECF6","gridcolor":"white","linecolor":"white","showbackground":true,"ticks":"","zerolinecolor":"white","gridwidth":2},"yaxis":{"backgroundcolor":"#E5ECF6","gridcolor":"white","linecolor":"white","showbackground":true,"ticks":"","zerolinecolor":"white","gridwidth":2},"zaxis":{"backgroundcolor":"#E5ECF6","gridcolor":"white","linecolor":"white","showbackground":true,"ticks":"","zerolinecolor":"white","gridwidth":2}},"shapedefaults":{"line":{"color":"#2a3f5f"}},"annotationdefaults":{"arrowcolor":"#2a3f5f","arrowhead":0,"arrowwidth":1},"geo":{"bgcolor":"white","landcolor":"#E5ECF6","subunitcolor":"white","showland":true,"showlakes":true,"lakecolor":"white"},"title":{"x":0.05},"mapbox":{"style":"light"}}},"xaxis":{"anchor":"y","domain":[0.0,1.0],"title":{"text":"Year"},"range":[2004.5,2021.5],"tickmode":"array","tickvals":[2005,2015,2021],"ticktext":[2005,2015,2021],"tickangle":45},"yaxis":{"anchor":"x","domain":[0.0,1.0],"title":{"text":"Total Ocean GDP"},"range":[0,46.74745488503653]},"legend":{"tracegroupgap":0,"itemsizing":"constant"},"margin":{"t":60},"height":600,"width":800,"updatemenus":[{"buttons":[{"args":[null,{"frame":{"duration":500,"redraw":false},"mode":"immediate","fromcurrent":true,"transition":{"duration":500,"easing":"linear"}}],"label":"&#9654;","method":"animate"},{"args":[[null],{"frame":{"duration":0,"redraw":false},"mode":"immediate","fromcurrent":true,"transition":{"duration":0,"easing":"linear"}}],"label":"&#9724;","method":"animate"}],"direction":"left","pad":{"r":10,"t":70},"showactive":false,"type":"buttons","x":0.1,"xanchor":"right","y":0,"yanchor":"top"}],"sliders":[{"active":0,"currentvalue":{"prefix":"State="},"len":0.9,"pad":{"b":10,"t":60},"steps":[{"args":[["Alabama"],{"frame":{"duration":0,"redraw":false},"mode":"immediate","fromcurrent":true,"transition":{"duration":0,"easing":"linear"}}],"label":"Alabama","method":"animate"},{"args":[["Delaware"],{"frame":{"duration":0,"redraw":false},"mode":"immediate","fromcurrent":true,"transition":{"duration":0,"easing":"linear"}}],"label":"Delaware","method":"animate"},{"args":[["Florida"],{"frame":{"duration":0,"redraw":false},"mode":"immediate","fromcurrent":true,"transition":{"duration":0,"easing":"linear"}}],"label":"Florida","method":"animate"},{"args":[["Georgia"],{"frame":{"duration":0,"redraw":false},"mode":"immediate","fromcurrent":true,"transition":{"duration":0,"easing":"linear"}}],"label":"Georgia","method":"animate"},{"args":[["Louisiana"],{"frame":{"duration":0,"redraw":false},"mode":"immediate","fromcurrent":true,"transition":{"duration":0,"easing":"linear"}}],"label":"Louisiana","method":"animate"},{"args":[["Maine"],{"frame":{"duration":0,"redraw":false},"mode":"immediate","fromcurrent":true,"transition":{"duration":0,"easing":"linear"}}],"label":"Maine","method":"animate"},{"args":[["Maryland"],{"frame":{"duration":0,"redraw":false},"mode":"immediate","fromcurrent":true,"transition":{"duration":0,"easing":"linear"}}],"label":"Maryland","method":"animate"},{"args":[["Massachusetts"],{"frame":{"duration":0,"redraw":false},"mode":"immediate","fromcurrent":true,"transition":{"duration":0,"easing":"linear"}}],"label":"Massachusetts","method":"animate"},{"args":[["Mississippi"],{"frame":{"duration":0,"redraw":false},"mode":"immediate","fromcurrent":true,"transition":{"duration":0,"easing":"linear"}}],"label":"Mississippi","method":"animate"},{"args":[["New Jersey"],{"frame":{"duration":0,"redraw":false},"mode":"immediate","fromcurrent":true,"transition":{"duration":0,"easing":"linear"}}],"label":"New Jersey","method":"animate"},{"args":[["New York"],{"frame":{"duration":0,"redraw":false},"mode":"immediate","fromcurrent":true,"transition":{"duration":0,"easing":"linear"}}],"label":"New York","method":"animate"},{"args":[["North Carolina"],{"frame":{"duration":0,"redraw":false},"mode":"immediate","fromcurrent":true,"transition":{"duration":0,"easing":"linear"}}],"label":"North Carolina","method":"animate"},{"args":[["Rhode Island"],{"frame":{"duration":0,"redraw":false},"mode":"immediate","fromcurrent":true,"transition":{"duration":0,"easing":"linear"}}],"label":"Rhode Island","method":"animate"},{"args":[["South Carolina"],{"frame":{"duration":0,"redraw":false},"mode":"immediate","fromcurrent":true,"transition":{"duration":0,"easing":"linear"}}],"label":"South Carolina","method":"animate"},{"args":[["Texas"],{"frame":{"duration":0,"redraw":false},"mode":"immediate","fromcurrent":true,"transition":{"duration":0,"easing":"linear"}}],"label":"Texas","method":"animate"},{"args":[["Virginia"],{"frame":{"duration":0,"redraw":false},"mode":"immediate","fromcurrent":true,"transition":{"duration":0,"easing":"linear"}}],"label":"Virginia","method":"animate"}],"x":0.1,"xanchor":"left","y":0,"yanchor":"top"}]},"frames":[{"data":[{"hovertemplate":"\u003cb\u003e%{hovertext}\u003c\u002fb\u003e\u003cbr\u003e\u003cbr\u003eState=Alabama\u003cbr\u003eYear=%{x}\u003cbr\u003eTotal Ocean GDP=%{marker.size}\u003cextra\u003e\u003c\u002fextra\u003e","hovertext":[42.068312301726806,44.57310192057757,45.47873299859467],"legendgroup":"","marker":{"color":"#636efa","size":[42.068312301726806,44.57310192057757,45.47873299859467],"sizemode":"area","sizeref":0.11436863721259133,"symbol":"circle"},"mode":"markers","name":"","orientation":"v","showlegend":false,"x":[2005,2015,2021],"xaxis":"x","y":[42.068312301726806,44.57310192057757,45.47873299859467],"yaxis":"y","type":"scatter"}],"name":"Alabama"},{"data":[{"hovertemplate":"\u003cb\u003e%{hovertext}\u003c\u002fb\u003e\u003cbr\u003e\u003cbr\u003eState=Delaware\u003cbr\u003eYear=%{x}\u003cbr\u003eTotal Ocean GDP=%{marker.size}\u003cextra\u003e\u003c\u002fextra\u003e","hovertext":[33.333333333333336,33.333333271038406,33.333333333333336],"legendgroup":"","marker":{"color":"#636efa","size":[33.333333333333336,33.333333271038406,33.333333333333336],"sizemode":"area","sizeref":0.11436863721259133,"symbol":"circle"},"mode":"markers","name":"","orientation":"v","showlegend":false,"x":[2005,2015,2021],"xaxis":"x","y":[33.333333333333336,33.333333271038406,33.333333333333336],"yaxis":"y","type":"scatter"}],"name":"Delaware"},{"data":[{"hovertemplate":"\u003cb\u003e%{hovertext}\u003c\u002fb\u003e\u003cbr\u003e\u003cbr\u003eState=Florida\u003cbr\u003eYear=%{x}\u003cbr\u003eTotal Ocean GDP=%{marker.size}\u003cextra\u003e\u003c\u002fextra\u003e","hovertext":[3.6692505191059137,3.7432574333701822,3.6158435335134382],"legendgroup":"","marker":{"color":"#636efa","size":[3.6692505191059137,3.7432574333701822,3.6158435335134382],"sizemode":"area","sizeref":0.11436863721259133,"symbol":"circle"},"mode":"markers","name":"","orientation":"v","showlegend":false,"x":[2005,2015,2021],"xaxis":"x","y":[3.6692505191059137,3.7432574333701822,3.6158435335134382],"yaxis":"y","type":"scatter"}],"name":"Florida"},{"data":[{"hovertemplate":"\u003cb\u003e%{hovertext}\u003c\u002fb\u003e\u003cbr\u003e\u003cbr\u003eState=Georgia\u003cbr\u003eYear=%{x}\u003cbr\u003eTotal Ocean GDP=%{marker.size}\u003cextra\u003e\u003c\u002fextra\u003e","hovertext":[35.15080761381264,45.45728761731739,45.74745488503653],"legendgroup":"","marker":{"color":"#636efa","size":[35.15080761381264,45.45728761731739,45.74745488503653],"sizemode":"area","sizeref":0.11436863721259133,"symbol":"circle"},"mode":"markers","name":"","orientation":"v","showlegend":false,"x":[2005,2015,2021],"xaxis":"x","y":[35.15080761381264,45.45728761731739,45.74745488503653],"yaxis":"y","type":"scatter"}],"name":"Georgia"},{"data":[{"hovertemplate":"\u003cb\u003e%{hovertext}\u003c\u002fb\u003e\u003cbr\u003e\u003cbr\u003eState=Louisiana\u003cbr\u003eYear=%{x}\u003cbr\u003eTotal Ocean GDP=%{marker.size}\u003cextra\u003e\u003c\u002fextra\u003e","hovertext":[14.304705355212281,13.063328110961866,12.583408271514617],"legendgroup":"","marker":{"color":"#636efa","size":[14.304705355212281,13.063328110961866,12.583408271514617],"sizemode":"area","sizeref":0.11436863721259133,"symbol":"circle"},"mode":"markers","name":"","orientation":"v","showlegend":false,"x":[2005,2015,2021],"xaxis":"x","y":[14.304705355212281,13.063328110961866,12.583408271514617],"yaxis":"y","type":"scatter"}],"name":"Louisiana"},{"data":[{"hovertemplate":"\u003cb\u003e%{hovertext}\u003c\u002fb\u003e\u003cbr\u003e\u003cbr\u003eState=Maine\u003cbr\u003eYear=%{x}\u003cbr\u003eTotal Ocean GDP=%{marker.size}\u003cextra\u003e\u003c\u002fextra\u003e","hovertext":[28.933164872412505,30.392173486790533,30.528911007587194],"legendgroup":"","marker":{"color":"#636efa","size":[28.933164872412505,30.392173486790533,30.528911007587194],"sizemode":"area","sizeref":0.11436863721259133,"symbol":"circle"},"mode":"markers","name":"","orientation":"v","showlegend":false,"x":[2005,2015,2021],"xaxis":"x","y":[28.933164872412505,30.392173486790533,30.528911007587194],"yaxis":"y","type":"scatter"}],"name":"Maine"},{"data":[{"hovertemplate":"\u003cb\u003e%{hovertext}\u003c\u002fb\u003e\u003cbr\u003e\u003cbr\u003eState=Maryland\u003cbr\u003eYear=%{x}\u003cbr\u003eTotal Ocean GDP=%{marker.size}\u003cextra\u003e\u003c\u002fextra\u003e","hovertext":[11.763564619157627,12.051786708524851,12.469198100190738],"legendgroup":"","marker":{"color":"#636efa","size":[11.763564619157627,12.051786708524851,12.469198100190738],"sizemode":"area","sizeref":0.11436863721259133,"symbol":"circle"},"mode":"markers","name":"","orientation":"v","showlegend":false,"x":[2005,2015,2021],"xaxis":"x","y":[11.763564619157627,12.051786708524851,12.469198100190738],"yaxis":"y","type":"scatter"}],"name":"Maryland"},{"data":[{"hovertemplate":"\u003cb\u003e%{hovertext}\u003c\u002fb\u003e\u003cbr\u003e\u003cbr\u003eState=Massachusetts\u003cbr\u003eYear=%{x}\u003cbr\u003eTotal Ocean GDP=%{marker.size}\u003cextra\u003e\u003c\u002fextra\u003e","hovertext":[10.906125341644392,10.989974130397448,13.119142567872904],"legendgroup":"","marker":{"color":"#636efa","size":[10.906125341644392,10.989974130397448,13.119142567872904],"sizemode":"area","sizeref":0.11436863721259133,"symbol":"circle"},"mode":"markers","name":"","orientation":"v","showlegend":false,"x":[2005,2015,2021],"xaxis":"x","y":[10.906125341644392,10.989974130397448,13.119142567872904],"yaxis":"y","type":"scatter"}],"name":"Massachusetts"},{"data":[{"hovertemplate":"\u003cb\u003e%{hovertext}\u003c\u002fb\u003e\u003cbr\u003e\u003cbr\u003eState=Mississippi\u003cbr\u003eYear=%{x}\u003cbr\u003eTotal Ocean GDP=%{marker.size}\u003cextra\u003e\u003c\u002fextra\u003e","hovertext":[35.33575832230989,40.18265324247956,40.25209099870287],"legendgroup":"","marker":{"color":"#636efa","size":[35.33575832230989,40.18265324247956,40.25209099870287],"sizemode":"area","sizeref":0.11436863721259133,"symbol":"circle"},"mode":"markers","name":"","orientation":"v","showlegend":false,"x":[2005,2015,2021],"xaxis":"x","y":[35.33575832230989,40.18265324247956,40.25209099870287],"yaxis":"y","type":"scatter"}],"name":"Mississippi"},{"data":[{"hovertemplate":"\u003cb\u003e%{hovertext}\u003c\u002fb\u003e\u003cbr\u003e\u003cbr\u003eState=New Jersey\u003cbr\u003eYear=%{x}\u003cbr\u003eTotal Ocean GDP=%{marker.size}\u003cextra\u003e\u003c\u002fextra\u003e","hovertext":[5.147801866601489,7.144540072164688,7.914347750936818],"legendgroup":"","marker":{"color":"#636efa","size":[5.147801866601489,7.144540072164688,7.914347750936818],"sizemode":"area","sizeref":0.11436863721259133,"symbol":"circle"},"mode":"markers","name":"","orientation":"v","showlegend":false,"x":[2005,2015,2021],"xaxis":"x","y":[5.147801866601489,7.144540072164688,7.914347750936818],"yaxis":"y","type":"scatter"}],"name":"New Jersey"},{"data":[{"hovertemplate":"\u003cb\u003e%{hovertext}\u003c\u002fb\u003e\u003cbr\u003e\u003cbr\u003eState=New York\u003cbr\u003eYear=%{x}\u003cbr\u003eTotal Ocean GDP=%{marker.size}\u003cextra\u003e\u003c\u002fextra\u003e","hovertext":[3.195834279509455,2.9099024754405605,4.9894417110198575],"legendgroup":"","marker":{"color":"#636efa","size":[3.195834279509455,2.9099024754405605,4.9894417110198575],"sizemode":"area","sizeref":0.11436863721259133,"symbol":"circle"},"mode":"markers","name":"","orientation":"v","showlegend":false,"x":[2005,2015,2021],"xaxis":"x","y":[3.195834279509455,2.9099024754405605,4.9894417110198575],"yaxis":"y","type":"scatter"}],"name":"New York"},{"data":[{"hovertemplate":"\u003cb\u003e%{hovertext}\u003c\u002fb\u003e\u003cbr\u003e\u003cbr\u003eState=North Carolina\u003cbr\u003eYear=%{x}\u003cbr\u003eTotal Ocean GDP=%{marker.size}\u003cextra\u003e\u003c\u002fextra\u003e","hovertext":[11.45460762837527,10.949613638082509,11.075671236752372],"legendgroup":"","marker":{"color":"#636efa","size":[11.45460762837527,10.949613638082509,11.075671236752372],"sizemode":"area","sizeref":0.11436863721259133,"symbol":"circle"},"mode":"markers","name":"","orientation":"v","showlegend":false,"x":[2005,2015,2021],"xaxis":"x","y":[11.45460762837527,10.949613638082509,11.075671236752372],"yaxis":"y","type":"scatter"}],"name":"North Carolina"},{"data":[{"hovertemplate":"\u003cb\u003e%{hovertext}\u003c\u002fb\u003e\u003cbr\u003e\u003cbr\u003eState=Rhode Island\u003cbr\u003eYear=%{x}\u003cbr\u003eTotal Ocean GDP=%{marker.size}\u003cextra\u003e\u003c\u002fextra\u003e","hovertext":[23.3198114402875,33.75363315866039,32.52215009048353],"legendgroup":"","marker":{"color":"#636efa","size":[23.3198114402875,33.75363315866039,32.52215009048353],"sizemode":"area","sizeref":0.11436863721259133,"symbol":"circle"},"mode":"markers","name":"","orientation":"v","showlegend":false,"x":[2005,2015,2021],"xaxis":"x","y":[23.3198114402875,33.75363315866039,32.52215009048353],"yaxis":"y","type":"scatter"}],"name":"Rhode Island"},{"data":[{"hovertemplate":"\u003cb\u003e%{hovertext}\u003c\u002fb\u003e\u003cbr\u003e\u003cbr\u003eState=South Carolina\u003cbr\u003eYear=%{x}\u003cbr\u003eTotal Ocean GDP=%{marker.size}\u003cextra\u003e\u003c\u002fextra\u003e","hovertext":[29.402138094201902,27.58991292612531,29.407881457364777],"legendgroup":"","marker":{"color":"#636efa","size":[29.402138094201902,27.58991292612531,29.407881457364777],"sizemode":"area","sizeref":0.11436863721259133,"symbol":"circle"},"mode":"markers","name":"","orientation":"v","showlegend":false,"x":[2005,2015,2021],"xaxis":"x","y":[29.402138094201902,27.58991292612531,29.407881457364777],"yaxis":"y","type":"scatter"}],"name":"South Carolina"},{"data":[{"hovertemplate":"\u003cb\u003e%{hovertext}\u003c\u002fb\u003e\u003cbr\u003e\u003cbr\u003eState=Texas\u003cbr\u003eYear=%{x}\u003cbr\u003eTotal Ocean GDP=%{marker.size}\u003cextra\u003e\u003c\u002fextra\u003e","hovertext":[0.8623966430532668,1.1423484494248055,1.1367264478543913],"legendgroup":"","marker":{"color":"#636efa","size":[0.8623966430532668,1.1423484494248055,1.1367264478543913],"sizemode":"area","sizeref":0.11436863721259133,"symbol":"circle"},"mode":"markers","name":"","orientation":"v","showlegend":false,"x":[2005,2015,2021],"xaxis":"x","y":[0.8623966430532668,1.1423484494248055,1.1367264478543913],"yaxis":"y","type":"scatter"}],"name":"Texas"},{"data":[{"hovertemplate":"\u003cb\u003e%{hovertext}\u003c\u002fb\u003e\u003cbr\u003e\u003cbr\u003eState=Virginia\u003cbr\u003eYear=%{x}\u003cbr\u003eTotal Ocean GDP=%{marker.size}\u003cextra\u003e\u003c\u002fextra\u003e","hovertext":[6.356923882652751,5.19646773955517,4.792890364582448],"legendgroup":"","marker":{"color":"#636efa","size":[6.356923882652751,5.19646773955517,4.792890364582448],"sizemode":"area","sizeref":0.11436863721259133,"symbol":"circle"},"mode":"markers","name":"","orientation":"v","showlegend":false,"x":[2005,2015,2021],"xaxis":"x","y":[6.356923882652751,5.19646773955517,4.792890364582448],"yaxis":"y","type":"scatter"}],"name":"Virginia"}]}